whitebox_plugin_adsb_gps/__init__.py
whitebox_plugin_adsb_gps/static/whitebox_plugin_adsb_gps/whitebox_plugin_adsb_gps.js
whitebox_plugin_adsb_gps/templates/whitebox_plugin_adsb_gps/whitebox_plugin_adsb_gps.html
whitebox_plugin_adsb_gps/whitebox_plugin_adsb_gps.py
whitebox_test_plugin_adsb_gps/__init__.py
whitebox_test_plugin_adsb_gps/test_whitebox_plugin_adsb_gps.py
whitebox_test_plugin_adsb_gps/test_whitebox_plugin_adsb_gps_browser.py
whitebox_test_plugin_adsb_gps/test_whitebox_plugin_adsb_gps_integration.py
whitebox_plugin_adsb_gps-0.1.0.dist-info/LICENSE
whitebox_plugin_adsb_gps-0.1.0.dist-info/METADATA
whitebox_plugin_adsb_gps-0.1.0.dist-info/WHEEL
whitebox_plugin_adsb_gps-0.1.0.dist-info/RECORD
